setup.py
bibtexprune/__init__.py
bibtexprune/command.py
bibtexprune.egg-info/PKG-INFO
bibtexprune.egg-info/SOURCES.txt
bibtexprune.egg-info/dependency_links.txt
bibtexprune.egg-info/entry_points.txt
bibtexprune.egg-info/requires.txt
bibtexprune.egg-info/top_level.txt