Metadata-Version: 1.1
Name: bibtexprune
Version: 1.0
Summary: Prune a large Bibtex database. extract only those entries necessary for
Home-page: https://github.com/wwaites/bibtexprune
Author: William Waites
Author-email: UNKNOWN
License: UNKNOWN
Platform: UNKNOWN
Classifier: Environment :: Console
Classifier: Intended Audience :: End Users/Desktop
Classifier: License :: OSI Approved :: GNU General Public License v3 or later (GPLv3+)
Classifier: Operating System :: POSIX
Classifier: Programming Language :: Python
Classifier: Topic :: Text Processing :: Markup :: LaTeX
